{
	"id": "gitlab",
	"name": "GitLab",
	"layer": "building-blocks",
	"sublayer": "inbetriebnahme",
	"description": {
		"de": "GitLab ist eine Plattform für den gesamten DevSecOps-Lebenszyklus. GitLab bietet Funktionen für Versionskontrolle (basierend auf Git), Projektplanung, Continuous Integration/Continuous Deployment (CI/CD), Code-Überprüfung, Sicherheitsscans und Fehlerverfolgung in einer einzigen Umgebung.",
		"en": ""
	},
	"homepage": "https://about.gitlab.com/",
	"logo": "https://commons.wikimedia.org/wiki/Special:FilePath/GitLab_logo.svg",
	"tags": ["pipeline", "cd", "bereitstellung", "ci"],
	"oss": true,
	"maturity": "graduated",
	"sovereigntyCriteria": {
		"openSource": true,
		"euHeadquartered": false,
		"hasAudit": true,
		"permissiveLicense": false,
		"matureProject": true,
		"largeEcosystem": false,
		"ownerType": "corporation"
	},
	"audit": {
		"lastDate": "2025-11-11",
		"url": "https://github.com/gitlabhq/gitlabhq"
	}
}
